{
  "symbol": "SPY",
  "asOf": "2026-07-06T15:10:20Z",
  "price": 749.92,
  "prevClose": 744.78,
  "change": 5.14,
  "changePct": 0.691,
  "open": 748.59,
  "dayHigh": 750.17,
  "dayLow": 747.41,
  "volume": 10916328,
  "vix": 16.01,
  "dailyMovePct": 0.591,
  "spark": [
    749.16,
    748.29,
    748.64,
    748.94,
    748.88,
    748.5,
    748.38,
    748.81,
    749.4,
    749.18,
    749.65,
    749.94,
    749.7,
    749.67,
    749.67,
    749.75,
    749.89,
    750.26,
    750.18,
    750.25,
    750.26
  ]
}